deps_rocker/__init__.py
deps_rocker/buildkit.py
deps_rocker/command_layer.py
deps_rocker/dependencies.py
deps_rocker/docker_cli.py
deps_rocker/docker_sdk.py
deps_rocker/rocker_patch.py
deps_rocker/simple_rocker_extension.py
deps_rocker/extensions/__init__.py
deps_rocker/extensions/auto/__init__.py
deps_rocker/extensions/auto/auto.py
deps_rocker/extensions/auto/test.sh
deps_rocker/extensions/cargo/__init__.py
deps_rocker/extensions/cargo/auto_detect.yml
deps_rocker/extensions/cargo/cargo.py
deps_rocker/extensions/cargo/cargo_builder_snippet.Dockerfile
deps_rocker/extensions/cargo/cargo_snippet.Dockerfile
deps_rocker/extensions/cargo/test.sh
deps_rocker/extensions/ccache/__init__.py
deps_rocker/extensions/ccache/auto_detect.yml
deps_rocker/extensions/ccache/ccache.py
deps_rocker/extensions/ccache/ccache_snippet.Dockerfile
deps_rocker/extensions/ccache/test.sh
deps_rocker/extensions/claude/README.md
deps_rocker/extensions/claude/__init__.py
deps_rocker/extensions/claude/auto_detect.yml
deps_rocker/extensions/claude/claude.py
deps_rocker/extensions/claude/claude_builder_snippet.Dockerfile
deps_rocker/extensions/claude/claude_snippet.Dockerfile
deps_rocker/extensions/claude/claude_user_snippet.Dockerfile
deps_rocker/extensions/claude/test.sh
deps_rocker/extensions/codex/__init__.py
deps_rocker/extensions/codex/auto_detect.yml
deps_rocker/extensions/codex/codex.py
deps_rocker/extensions/codex/codex_snippet.Dockerfile
deps_rocker/extensions/codex/test.sh
deps_rocker/extensions/conda/__init__.py
deps_rocker/extensions/conda/auto_detect.yml
deps_rocker/extensions/conda/conda.py
deps_rocker/extensions/conda/conda_builder_snippet.Dockerfile
deps_rocker/extensions/conda/conda_snippet.Dockerfile
deps_rocker/extensions/conda/conda_user_snippet.Dockerfile
deps_rocker/extensions/conda/test.sh
deps_rocker/extensions/curl/__init__.py
deps_rocker/extensions/curl/curl.py
deps_rocker/extensions/curl/test.sh
deps_rocker/extensions/cwd/__init__.py
deps_rocker/extensions/cwd/cwd.py
deps_rocker-0.23.1.dist-info/METADATA
deps_rocker-0.23.1.dist-info/WHEEL
deps_rocker-0.23.1.dist-info/entry_points.txt
deps_rocker-0.23.1.dist-info/licenses/LICENSE
deps_rocker-0.23.1.dist-info/RECORD
