Metadata-Version: 2.4
Name: deps_rocker
Version: 0.23.1
Summary: A rocker plugin to help installing apt and pip dependencies
Project-URL: Source, https://github.com/blooop/deps_rocker
Project-URL: Home, https://github.com/blooop/deps_rocker
Author-email: Austin Gregg-Smith <blooop@gmail.com>
License-Expression: MIT
License-File: LICENSE
Requires-Python: >=3.9
Requires-Dist: off-your-rocker>=0.1.0
Requires-Dist: pyyaml>=5.0
Requires-Dist: rocker>=0.2.19
Requires-Dist: toml>=0.10
